pytinyurl.py
pytinyurl-1.0.0.dist-info/LICENSE
pytinyurl-1.0.0.dist-info/METADATA
pytinyurl-1.0.0.dist-info/WHEEL
pytinyurl-1.0.0.dist-info/entry_points.txt
pytinyurl-1.0.0.dist-info/top_level.txt
pytinyurl-1.0.0.dist-info/RECORD
